{
  "1": {
    "inputs": {
      "filename_prefix": "ltx2_outputs/",
      "images": ["8", 0]
    },
    "class_type": "SaveImage",
    "_meta": {"title": "Save Video"}
  },
  "2": {
    "inputs": {
      "string": "cinematic motion, natural movement, professional camera work, slow pan, subtle zoom, cinematic lighting, 4k quality"
    },
    "class_type": "PrimitiveNode",
    "_meta": {"title": "Motion Prompt"}
  },
  "3": {
    "inputs": {
      "text": ["2", 0],
      "clip": ["22", 0]
    },
    "class_type": "CLIPTextEncode",
    "_meta": {"title": "Positive Prompt"}
  },
  "4": {
    "inputs": {"string": ""},
    "class_type": "PrimitiveNode",
    "_meta": {"title": "Negative Prompt"}
  },
  "5": {
    "inputs": {
      "text": ["4", 0],
      "clip": ["22", 0]
    },
    "class_type": "CLIPTextEncode",
    "_meta": {"title": "Negative Encode"}
  },
  "6": {
    "inputs": {
      "input_image": ["20", 0],
      "vae": ["21", 0]
    },
    "class_type": "VAEEncode",
    "_meta": {"title": "VAE Encode Image"}
  },
  "8": {
    "inputs": {
      "samples": ["10", 0],
      "vae": ["21", 0]
    },
    "class_type": "VAEDecode",
    "_meta": {"title": "VAE Decode"}
  },
  "10": {
    "inputs": {
      "seed": 0,
      "steps": 30,
      "cfg": 7.5,
      "sampler_name": "euler",
      "scheduler": "karras",
      "denoise": 0.7,
      "model": ["11", 0],
      "positive": ["3", 0],
      "negative": ["5", 0],
      "latent_image": ["6", 0]
    },
    "class_type": "KSampler",
    "_meta": {"title": "KSampler"}
  },
  "11": {
    "inputs": {"ckpt_name": "LTX-Video-2B-v0.9.safetensors"},
    "class_type": "CheckpointLoaderSimple",
    "_meta": {"title": "Load LTX-2 Model"}
  },
  "14": {
    "inputs": {
      "format": "video/h264-mp4",
      "pix_fmt": "yuv420p",
      "crf": 19,
      "frame_rate": 24,
      "loop_count": 0,
      "filename_prefix": "ltx2_video/",
      "pingpong": false,
      "save_output": true,
      "images": ["8", 0],
      "audio": ["15", 0]
    },
    "class_type": "VHS_VideoCombine",
    "_meta": {"title": "Video Combine + Audio"}
  },
  "15": {
    "inputs": {
      "audio": "background_music.mp3",
      "audioUI": ""
    },
    "class_type": "LoadAudio",
    "_meta": {"title": "Load Audio"}
  },
  "20": {
    "inputs": {
      "image": "reference_image.png",
      "imageUI": ""
    },
    "class_type": "LoadImage",
    "_meta": {"title": "Load Image"}
  },
  "21": {
    "inputs": {"vae_name": "vae-ft-mse-840000-ema-pruned.safetensors"},
    "class_type": "VAELoader",
    "_meta": {"title": "Load VAE"}
  },
  "22": {
    "inputs": {"clip_name": "t5-v1_1-xxl-encoder-q8.safetensors"},
    "class_type": "CLIPLoader",
    "_meta": {"title": "Load CLIP"}
  }
}
